dm_utils/__init__.py
dm_utils/hom.py
dm_utils/oof.py
dm_utils/runner.py
dm_utils/evaluate/__init__.py
dm_utils/evaluate/metric.py
dm_utils/evaluate/score.py
dm_utils/param/__init__.py
dm_utils/param/param_base.py
dm_utils/param/param_cb.py
dm_utils/param/param_lgb.py
dm_utils/param/param_xgb.py
dm_utils/task/__init__.py
dm_utils/task/task_cls.py
dm_utils/task/task_reg.py
dm_utils/utils/__init__.py
dm_utils/utils/base.py
dm_utils/utils/cprint.py
dm_utils/utils/feas.py
dm_utils/utils/tree.py
dm_utils-0.1.1.data/data/requirements.txt
dm_utils-0.1.1.dist-info/LICENSE
dm_utils-0.1.1.dist-info/METADATA
dm_utils-0.1.1.dist-info/WHEEL
dm_utils-0.1.1.dist-info/top_level.txt
dm_utils-0.1.1.dist-info/RECORD
