Metadata-Version: 2.1
Name: dm_utils
Version: 0.1.1
Summary: Data Mining Utils
Home-page: https://pypi.org/project/dm_utils/
Author: Mingze He
Author-email: hemingze126@126.com
Classifier: Programming Language :: Python :: 3
Classifier: License :: OSI Approved :: Apache Software License
Classifier: Operating System :: OS Independent
License-File: LICENSE
Requires-Dist: catboost ~=1.2.5
Requires-Dist: colorama ~=0.4.6
Requires-Dist: ipython ~=8.26.0
Requires-Dist: joblib ~=1.4.2
Requires-Dist: lightgbm ~=4.3.0
Requires-Dist: matplotlib ~=3.9.0
Requires-Dist: ngboost ~=0.5.1
Requires-Dist: numpy ~=1.26.4
Requires-Dist: pandas ~=2.2.2
Requires-Dist: pytorch-tabnet ~=4.1.0
Requires-Dist: scikit-learn ~=1.4.0
Requires-Dist: scipy ~=1.12.0
Requires-Dist: seaborn ~=0.13.2
Requires-Dist: tqdm ~=4.66.5
Requires-Dist: xgboost ~=2.0.3
